controlx/__init__.py
controlx/control.py
controlx-0.0.0.1.dist-info/LICENCE.txt
controlx-0.0.0.1.dist-info/METADATA
controlx-0.0.0.1.dist-info/WHEEL
controlx-0.0.0.1.dist-info/top_level.txt
controlx-0.0.0.1.dist-info/RECORD
